nonebot_plugin_arkguesser/__init__.py
nonebot_plugin_arkguesser/game_tools/__init__.py
nonebot_plugin_arkguesser/game_tools/config.py
nonebot_plugin_arkguesser/game_tools/continuous_manager.py
nonebot_plugin_arkguesser/game_tools/game.py
nonebot_plugin_arkguesser/game_tools/mode_manager.py
nonebot_plugin_arkguesser/game_tools/pool_manager.py
nonebot_plugin_arkguesser/game_tools/render.py
nonebot_plugin_arkguesser/resource_tools/__init__.py
nonebot_plugin_arkguesser/resource_tools/illustration_config.py
nonebot_plugin_arkguesser/resource_tools/illustration_downloader_v2.py
nonebot_plugin_arkguesser/resource_tools/run_illustration_download.py
nonebot_plugin_arkguesser/resource_tools/update_simple.py
nonebot_plugin_arkguesser/resources/images/xlpj/血狼破军_B站头像.webp
nonebot_plugin_arkguesser/resources/templates/correct.html
nonebot_plugin_arkguesser/resources/templates/correct_rabbit.html
nonebot_plugin_arkguesser/resources/templates/guess.html
nonebot_plugin_arkguesser/resources/templates/guess_rabbit.html
nonebot_plugin_arkguesser-0.3.2.dist-info/METADATA
nonebot_plugin_arkguesser-0.3.2.dist-info/WHEEL
nonebot_plugin_arkguesser-0.3.2.dist-info/entry_points.txt
nonebot_plugin_arkguesser-0.3.2.dist-info/RECORD
