Metadata-Version: 2.4
Name: nonebot-plugin-arkguesser
Version: 0.3.2
Summary: 明日方舟猜干员游戏 - 支持多种游戏模式和题库设置
Project-URL: Homepage, https://github.com/lizhiqi233-rgb/nonebot-plugin-arkguesser
Project-URL: Repository, https://github.com/lizhiqi233-rgb/nonebot-plugin-arkguesser
Project-URL: Documentation, https://github.com/lizhiqi233-rgb/nonebot-plugin-arkguesser#readme
Project-URL: Issues, https://github.com/lizhiqi233-rgb/nonebot-plugin-arkguesser/issues
Project-URL: Discussions, https://github.com/lizhiqi233-rgb/nonebot-plugin-arkguesser/discussions
Author-email: lizhiqi233-rgb <lizhiqi233-rgb@example.com>
License: MIT
Keywords: arknights,game,guess,nonebot,nonebot2,plugin
Classifier: Development Status :: 4 - Beta
Classifier: License :: OSI Approved :: MIT License
Classifier: Programming Language :: Python :: 3
Classifier: Programming Language :: Python :: 3.9
Classifier: Programming Language :: Python :: 3.10
Classifier: Programming Language :: Python :: 3.11
Classifier: Programming Language :: Python :: 3.12
Classifier: Topic :: Communications :: Chat
Classifier: Topic :: Games/Entertainment
Requires-Python: >=3.9
Requires-Dist: httpx>=0.24.0
Requires-Dist: nonebot-plugin-alconna>=0.59.3
Requires-Dist: nonebot-plugin-htmlrender>=0.6.6
Requires-Dist: nonebot-plugin-localstore>=0.7.4
Requires-Dist: nonebot-plugin-uninfo>=0.9.0
Requires-Dist: nonebot2>=2.4.2
Requires-Dist: pillow>=9.0.0
Requires-Dist: pydantic>=1.10
Requires-Dist: pypinyin>=0.55.0
Provides-Extra: dev
Requires-Dist: black>=23.0.0; extra == 'dev'
Requires-Dist: flake8>=6.0.0; extra == 'dev'
Requires-Dist: isort>=5.12.0; extra == 'dev'
Requires-Dist: pytest-cov>=4.0.0; extra == 'dev'
Requires-Dist: pytest>=7.0.0; extra == 'dev'
